django_federated_foreign_key-0.1.3.dist-info/licenses/LICENSE
federated_foreign_key/__init__.py
federated_foreign_key/apps.py
federated_foreign_key/checks.py
federated_foreign_key/fields.py
federated_foreign_key/models.py
federated_foreign_key/prefetch.py
federated_foreign_key/views.py
federated_foreign_key/management/__init__.py
federated_foreign_key/management/create.py
federated_foreign_key/management/commands/remove_stale_generic_contenttypes.py
federated_foreign_key/migrations/0001_initial.py
federated_foreign_key/migrations/__init__.py
django_federated_foreign_key-0.1.3.dist-info/METADATA
django_federated_foreign_key-0.1.3.dist-info/WHEEL
django_federated_foreign_key-0.1.3.dist-info/top_level.txt
django_federated_foreign_key-0.1.3.dist-info/RECORD
