Metadata-Version: 2.4
Name: django-federated-foreign-key
Version: 0.1.3
Summary: GenericForeignKey that can reference objects across projects
Requires-Python: >=3.8
License-File: LICENSE
Requires-Dist: Django>=3.2
Dynamic: license-file
